dref/__init__.py
dref/_modidx.py
dref/_tmp.py
dref/core.py
dref-0.0.1.dist-info/LICENSE
dref-0.0.1.dist-info/METADATA
dref-0.0.1.dist-info/WHEEL
dref-0.0.1.dist-info/entry_points.txt
dref-0.0.1.dist-info/top_level.txt
dref-0.0.1.dist-info/RECORD
